fstore/__init__.py
fstore/__main__.py
fstore/binary_search_tree.py
FStore-1.0.2.dist-info/LICENSE.txt
FStore-1.0.2.dist-info/METADATA
FStore-1.0.2.dist-info/WHEEL
FStore-1.0.2.dist-info/entry_points.txt
FStore-1.0.2.dist-info/top_level.txt
FStore-1.0.2.dist-info/RECORD
