Metadata-Version: 2.1
Name: FStore
Version: 1.0.2
Summary: Key-value store in Python
Home-page: https://github.com/colin-m-davis/kvs
Author: Colin Davis
Author-email: colinmichaelsdavis@gmail.com
License: LICENSE.txt
License-File: LICENSE.txt
